{
  "last_updated": "2022-05-14T17:04:43Z",
  "activity": [
    {
      "type": "pr_opened",
      "title": "gtech-mulearn/Github-Enablment-Task#159",
      "time": "2022-05-14T17:04:43Z",
      "link": "https://github.com/gtech-mulearn/Github-Enablment-Task/pull/159",
      "text": "Develop"
    },
    {
      "type": "pr_merged",
      "title": "gtech-mulearn/Github-Enablment-Task#159",
      "time": "2022-06-18T20:03:35Z",
      "link": "https://github.com/gtech-mulearn/Github-Enablment-Task/pull/159",
      "text": "Develop"
    }
  ],
  "open_prs": [],
  "authored_issue_and_pr": []
}