{
  "last_updated": "2023-11-04T19:35:01Z",
  "activity": [
    {
      "type": "pr_opened",
      "title": "gtech-mulearn/Top-100-Coders#434",
      "time": "2023-11-04T19:35:01Z",
      "link": "https://github.com/gtech-mulearn/Top-100-Coders/pull/434",
      "text": "Create akshaysnair-1@mulearn.md"
    },
    {
      "type": "pr_merged",
      "title": "gtech-mulearn/Top-100-Coders#434",
      "time": "2023-11-05T06:42:43Z",
      "link": "https://github.com/gtech-mulearn/Top-100-Coders/pull/434",
      "text": "Create akshaysnair-1@mulearn.md"
    },
    {
      "type": "pr_opened",
      "title": "gtech-mulearn/Github-Enablment-Task#217",
      "time": "2022-05-15T14:11:39Z",
      "link": "https://github.com/gtech-mulearn/Github-Enablment-Task/pull/217",
      "text": "Develop"
    },
    {
      "type": "pr_opened",
      "title": "gtech-mulearn/Github-Enablment-Task#345",
      "time": "2022-06-03T10:33:43Z",
      "link": "https://github.com/gtech-mulearn/Github-Enablment-Task/pull/345",
      "text": "Modified assignment submission"
    },
    {
      "type": "pr_merged",
      "title": "gtech-mulearn/Github-Enablment-Task#345",
      "time": "2022-06-19T05:14:51Z",
      "link": "https://github.com/gtech-mulearn/Github-Enablment-Task/pull/345",
      "text": "Modified assignment submission"
    },
    {
      "type": "pr_opened",
      "title": "gtech-mulearn/bring-every-business-online#39",
      "time": "2023-06-19T19:04:19Z",
      "link": "https://github.com/gtech-mulearn/bring-every-business-online/pull/39",
      "text": "Akshay added Smitha bakery"
    },
    {
      "type": "pr_merged",
      "title": "gtech-mulearn/bring-every-business-online#39",
      "time": "2023-06-20T18:24:25Z",
      "link": "https://github.com/gtech-mulearn/bring-every-business-online/pull/39",
      "text": "Akshay added Smitha bakery"
    }
  ],
  "open_prs": [],
  "authored_issue_and_pr": []
}