{
  "last_updated": "2023-10-08T10:00:13Z",
  "activity": [
    {
      "type": "pr_opened",
      "title": "gtech-mulearn/Top-100-Coders#167",
      "time": "2023-10-08T10:00:13Z",
      "link": "https://github.com/gtech-mulearn/Top-100-Coders/pull/167",
      "text": "chithralekha.m.p@mulearn"
    },
    {
      "type": "pr_merged",
      "title": "gtech-mulearn/Top-100-Coders#167",
      "time": "2023-10-08T11:07:28Z",
      "link": "https://github.com/gtech-mulearn/Top-100-Coders/pull/167",
      "text": "chithralekha.m.p@mulearn"
    }
  ],
  "open_prs": [],
  "authored_issue_and_pr": []
}