{
  "last_updated": "2024-03-30T17:01:08+00:00",
  "activity": [
    {
      "type": "pr_merged",
      "title": "gtech-mulearn/Github-Enablment-Task#516",
      "time": "2024-03-30T17:01:08+00:00",
      "link": "https://github.com/gtech-mulearn/Github-Enablment-Task/pull/516",
      "text": "eesa_bin_zakariyya_book_app",
      "turnaround_time": 5994
    },
    {
      "type": "comment_created",
      "title": "gtech-mulearn/Github-Enablment-Task#516",
      "time": "2024-03-30T15:21:38+00:00",
      "link": "https://github.com/gtech-mulearn/Github-Enablment-Task/pull/516#issuecomment-2028118111",
      "text": "Completed\r\n"
    },
    {
      "type": "pr_opened",
      "title": "gtech-mulearn/Github-Enablment-Task#516",
      "time": "2024-03-30T15:21:14+00:00",
      "link": "https://github.com/gtech-mulearn/Github-Enablment-Task/pull/516",
      "text": "eesa_bin_zakariyya_book_app"
    },
    {
      "type": "pr_opened",
      "title": "gtech-mulearn/Top-100-Coders#447",
      "time": "2023-11-08T13:26:13Z",
      "link": "https://github.com/gtech-mulearn/Top-100-Coders/pull/447",
      "text": "eesazakariyya@mulearn.md"
    },
    {
      "type": "pr_merged",
      "title": "gtech-mulearn/Top-100-Coders#447",
      "time": "2023-11-08T14:16:45Z",
      "link": "https://github.com/gtech-mulearn/Top-100-Coders/pull/447",
      "text": "eesazakariyya@mulearn.md"
    }
  ],
  "open_prs": [],
  "authored_issue_and_pr": []
}