{
  "last_updated": "2024-04-23T17:04:13+00:00",
  "activity": [
    {
      "type": "pr_merged",
      "title": "gtech-mulearn/IEEE-LAUNCHPAD#184",
      "time": "2024-04-23T17:04:13+00:00",
      "link": "https://github.com/gtech-mulearn/IEEE-LAUNCHPAD/pull/184",
      "text": "pavinraj@mulearn",
      "turnaround_time": 14763
    },
    {
      "type": "pr_reviewed",
      "time": "2024-04-23T13:18:41+00:00",
      "title": "gtech-mulearn/IEEE-LAUNCHPAD#184",
      "link": "https://github.com/gtech-mulearn/IEEE-LAUNCHPAD/pull/184#pullrequestreview-2017248987",
      "text": "pavinraj@mulearn"
    },
    {
      "type": "pr_opened",
      "title": "gtech-mulearn/IEEE-LAUNCHPAD#184",
      "time": "2024-04-23T12:58:11+00:00",
      "link": "https://github.com/gtech-mulearn/IEEE-LAUNCHPAD/pull/184",
      "text": "pavinraj@mulearn"
    }
  ],
  "open_prs": [],
  "authored_issue_and_pr": []
}