{
  "last_updated": "2023-10-17T08:25:44Z",
  "activity": [
    {
      "type": "pr_opened",
      "title": "gtech-mulearn/Top-100-Coders#233",
      "time": "2023-10-17T08:25:44Z",
      "link": "https://github.com/gtech-mulearn/Top-100-Coders/pull/233",
      "text": "Create shaheemv-1@mulearn"
    },
    {
      "type": "pr_merged",
      "title": "gtech-mulearn/Top-100-Coders#233",
      "time": "2023-10-17T12:59:41Z",
      "link": "https://github.com/gtech-mulearn/Top-100-Coders/pull/233",
      "text": "Create shaheemv-1@mulearn"
    }
  ],
  "open_prs": [],
  "authored_issue_and_pr": []
}