{
  "last_updated": "2023-11-04T11:08:56Z",
  "activity": [
    {
      "type": "pr_opened",
      "title": "gtech-mulearn/Top-100-Coders#431",
      "time": "2023-11-04T11:08:56Z",
      "link": "https://github.com/gtech-mulearn/Top-100-Coders/pull/431",
      "text": "Create tinuskariah@mulearn.md"
    },
    {
      "type": "pr_merged",
      "title": "gtech-mulearn/Top-100-Coders#431",
      "time": "2023-11-04T14:03:16Z",
      "link": "https://github.com/gtech-mulearn/Top-100-Coders/pull/431",
      "text": "Create tinuskariah@mulearn.md"
    }
  ],
  "open_prs": [],
  "authored_issue_and_pr": []
}