{
  "last_updated": "2022-05-15T15:11:28Z",
  "activity": [
    {
      "type": "pr_opened",
      "title": "gtech-mulearn/Github-Enablment-Task#229",
      "time": "2022-05-15T15:11:28Z",
      "link": "https://github.com/gtech-mulearn/Github-Enablment-Task/pull/229",
      "text": "Vipin K P - TFP Assignment 3"
    },
    {
      "type": "pr_merged",
      "title": "gtech-mulearn/Github-Enablment-Task#229",
      "time": "2022-06-19T05:12:37Z",
      "link": "https://github.com/gtech-mulearn/Github-Enablment-Task/pull/229",
      "text": "Vipin K P - TFP Assignment 3"
    }
  ],
  "open_prs": [],
  "authored_issue_and_pr": []
}